[{"sub_ensp":"ENSP00000301607","sub_name":"EVPL","sub_position":1263,"sub_region":"VRHERSPEVLR","kinase_name":"","source":"psite;hprd","string_score":778},{"sub_ensp":"ENSP00000301607","sub_name":"EVPL","sub_position":1698,"sub_region":"TGKDMSPYEAY","kinase_name":"","source":"psite","string_score":778},{"sub_ensp":"ENSP00000301607","sub_name":"EVPL","sub_position":1799,"sub_region":"SIISKSPLASP","kinase_name":"","source":"psite;hprd","string_score":778},{"sub_ensp":"ENSP00000301607","sub_name":"EVPL","sub_position":18,"sub_region":"GSPKGSPAKGS","kinase_name":"","source":"hprd","string_score":778},{"sub_ensp":"ENSP00000301607","sub_name":"EVPL","sub_position":1813,"sub_region":"STSFFSPSFSL","kinase_name":"","source":"hprd","string_score":778},{"sub_ensp":"ENSP00000301607","sub_name":"EVPL","sub_position":2025,"sub_region":"CYRSASPTVPR","kinase_name":"","source":"psite;pelm;hprd","string_score":778},{"sub_ensp":"ENSP00000301607","sub_name":"EVPL","sub_position":23,"sub_region":"SPAKGSPKGSP","kinase_name":"","source":"psite","string_score":778},{"sub_ensp":"ENSP00000361066","sub_name":"NCOA3","sub_position":1330,"sub_region":"FGRVSSPPNAM","kinase_name":"","source":"psite;pelm;hprd","string_score":630},{"sub_ensp":"ENSP00000361066","sub_name":"NCOA3","sub_position":214,"sub_region":"EDINASPEMRQ","kinase_name":"","source":"psite;pelm;hprd","string_score":630},{"sub_ensp":"ENSP00000361066","sub_name":"NCOA3","sub_position":24,"sub_region":"KLPCDTPGQGL","kinase_name":"MAPK8","source":"psite;pelm;hprd","string_score":630},{"sub_ensp":"ENSP00000361066","sub_name":"NCOA3","sub_position":505,"sub_region":"VAGVHSPMASS","kinase_name":"MAPK14;MAPK8","source":"psite;pelm;hprd","string_score":630},{"sub_ensp":"ENSP00000361066","sub_name":"NCOA3","sub_position":543,"sub_region":"LSTLSSPGPKL","kinase_name":"MAPK14;MAPK8","source":"psite;pelm;hprd","string_score":630},{"sub_ensp":"ENSP00000361066","sub_name":"NCOA3","sub_position":551,"sub_region":"PKLDNSPNMNI","kinase_name":"","source":"psite;pelm;hprd","string_score":630},{"sub_ensp":"ENSP00000361066","sub_name":"NCOA3","sub_position":569,"sub_region":"NQDSKSPLGFY","kinase_name":"","source":"psite","string_score":630},{"sub_ensp":"ENSP00000361066","sub_name":"NCOA3","sub_position":694,"sub_region":"LQNGNSPAEVA","kinase_name":"","source":"psite;hprd","string_score":630},{"sub_ensp":"ENSP00000361066","sub_name":"NCOA3","sub_position":728,"sub_region":"KQEQLSPKKKE","kinase_name":"CDK1","source":"psite;pelm;hprd","string_score":630},{"sub_ensp":"ENSP00000361066","sub_name":"NCOA3","sub_position":860,"sub_region":"AVSLDSPVSVG","kinase_name":"MAPK14;MAPK8","source":"psite;pelm;hprd","string_score":630},{"sub_ensp":"ENSP00000361066","sub_name":"NCOA3","sub_position":867,"sub_region":"VSVGSSPPVKN","kinase_name":"CDK1;MAPK14;MAPK8","source":"psite;pelm;hprd","string_score":630},{"sub_ensp":"ENSP00000378529","sub_name":"FZR1","sub_position":121,"sub_region":"RLQPSTPEKKG","kinase_name":"CDK5","source":"psite","string_score":643},{"sub_ensp":"ENSP00000378529","sub_name":"FZR1","sub_position":138,"sub_region":"STKRSSPDDGN","kinase_name":"","source":"psite;pelm;hprd","string_score":643},{"sub_ensp":"ENSP00000378529","sub_name":"FZR1","sub_position":146,"sub_region":"DGNDVSPYSLS","kinase_name":"","source":"psite;pelm;hprd","string_score":643},{"sub_ensp":"ENSP00000378529","sub_name":"FZR1","sub_position":151,"sub_region":"SPYSLSPVSNK","kinase_name":"CDK2","source":"psite;pelm;hprd","string_score":643},{"sub_ensp":"ENSP00000378529","sub_name":"FZR1","sub_position":163,"sub_region":"QKLLRSPRKPT","kinase_name":"CDK2;CDK5","source":"psite;pelm;hprd","string_score":643},{"sub_ensp":"ENSP00000378529","sub_name":"FZR1","sub_position":32,"sub_region":"MRRTLTPASSP","kinase_name":"","source":"psite;pelm;hprd","string_score":643},{"sub_ensp":"ENSP00000378529","sub_name":"FZR1","sub_position":36,"sub_region":"LTPASSPVSSP","kinase_name":"","source":"psite;pelm;hprd","string_score":643},{"sub_ensp":"ENSP00000378529","sub_name":"FZR1","sub_position":40,"sub_region":"SSPVSSPSKHG","kinase_name":"CDK5","source":"psite;pelm;hprd","string_score":643},{"sub_ensp":"ENSP00000378529","sub_name":"FZR1","sub_position":70,"sub_region":"NENEKSPSQNR","kinase_name":"","source":"psite;pelm","string_score":643}]
