[{"prot_id":"ENSP00000351908","prot_name":"MAP3K5","position":83,"flank":"RGRGSSVGGGS","kinase":"AKT1;AKT2;PIM1","source":"hprd;pelm;psite","string_score":985},{"prot_id":"ENSP00000351908","prot_name":"MAP3K5","position":966,"flank":"YLRSISLPVPV","kinase":"MAP3K5;PDPK1","source":"hprd;pelm;psite","string_score":985},{"prot_id":"ENSP00000264110","prot_name":"ATF2","position":62,"flank":"PARNDSVIVAD","kinase":"VRK1","source":"pelm;psite","string_score":581},{"prot_id":"ENSP00000264110","prot_name":"ATF2","position":307,"flank":"LVRTQSEESRP","kinase":"","source":"psite","string_score":581},{"prot_id":"ENSP00000288602","prot_name":"BRAF","position":363,"flank":"GQRDRSSSAPN","kinase":"","source":"hprd;psite","string_score":910},{"prot_id":"ENSP00000288602","prot_name":"BRAF","position":365,"flank":"RDRSSSAPNVH","kinase":"AKT1;AKT3","source":"hprd;pelm;psite","string_score":910},{"prot_id":"ENSP00000288602","prot_name":"BRAF","position":429,"flank":"RERKSSSSSED","kinase":"AKT1;AKT3","source":"hprd;pelm;psite","string_score":910},{"prot_id":"ENSP00000288602","prot_name":"BRAF","position":440,"flank":"RNRMKTLGRRD","kinase":"","source":"hprd;pelm;psite","string_score":910},{"prot_id":"ENSP00000288602","prot_name":"BRAF","position":446,"flank":"LGRRDSSDDWE","kinase":"PAK1","source":"hprd;pelm;psite","string_score":910},{"prot_id":"ENSP00000288602","prot_name":"BRAF","position":447,"flank":"GRRDSSDDWEI","kinase":"","source":"hprd;pelm;psite","string_score":910},{"prot_id":"ENSP00000288602","prot_name":"BRAF","position":465,"flank":"GQRIGSGSFGT","kinase":"","source":"psite","string_score":910},{"prot_id":"ENSP00000288602","prot_name":"BRAF","position":729,"flank":"IHRSASEPSLN","kinase":"","source":"hprd;pelm;psite","string_score":910},{"prot_id":"ENSP00000258682","prot_name":"CAMK2B","position":287,"flank":"MHRQETVECLK","kinase":"CAMK2B","source":"hprd;psite","string_score":903},{"prot_id":"ENSP00000370503","prot_name":"CCM2","position":414,"flank":"HRRALSTTSSS","kinase":"","source":"psite","string_score":952},{"prot_id":"ENSP00000245960","prot_name":"CDC25B","position":151,"flank":"IRRFQSMPVRL","kinase":"","source":"psite","string_score":442},{"prot_id":"ENSP00000245960","prot_name":"CDC25B","position":167,"flank":"VLRNITNSQAP","kinase":"","source":"psite","string_score":442},{"prot_id":"ENSP00000245960","prot_name":"CDC25B","position":178,"flank":"DGRRKSEAGSG","kinase":"","source":"psite","string_score":442},{"prot_id":"ENSP00000245960","prot_name":"CDC25B","position":230,"flank":"AQRPSSAPDLM","kinase":"CHEK1","source":"pelm;psite","string_score":442},{"prot_id":"ENSP00000245960","prot_name":"CDC25B","position":323,"flank":"LFRSPSMPCSV","kinase":"MAPKAPK2;MELK","source":"pelm;psite","string_score":442},{"prot_id":"ENSP00000245960","prot_name":"CDC25B","position":353,"flank":"NKRRRSVTPPE","kinase":"AURKA;MAPKAPK2;RPS6KA1","source":"hprd;pelm;psite","string_score":442},{"prot_id":"ENSP00000245960","prot_name":"CDC25B","position":375,"flank":"VLRSKSLCHDE","kinase":"BRSK1;MAPKAPK2","source":"hprd;pelm;psite","string_score":442},{"prot_id":"ENSP00000369213","prot_name":"DDX58","position":770,"flank":"ILRLQTWDEAV","kinase":"CSNK2A1","source":"psite","string_score":800},{"prot_id":"ENSP00000354791","prot_name":"DCTN1","position":1153,"flank":"LYRKTSQLLET","kinase":"","source":"psite","string_score":621},{"prot_id":"ENSP00000306245","prot_name":"FOS","position":362,"flank":"AHRKGSSSNEP","kinase":"PRKACA;RPS6KA1;RPS6KA3","source":"hprd;pelm;psite","string_score":542},{"prot_id":"ENSP00000310170","prot_name":"FOSL1","position":252,"flank":"AHRKSSSSSGD","kinase":"","source":"psite","string_score":479},{"prot_id":"ENSP00000263791","prot_name":"EIF2AK4","position":254,"flank":"RERQYSVCNSE","kinase":"","source":"psite","string_score":800},{"prot_id":"ENSP00000263791","prot_name":"EIF2AK4","position":572,"flank":"SNRLPSAAFFS","kinase":"","source":"psite","string_score":800},{"prot_id":"ENSP00000365439","prot_name":"HNRNPK","position":302,"flank":"GGRGGSRARNL","kinase":"PRKCD","source":"hprd;pelm;psite","string_score":686},{"prot_id":"ENSP00000320821","prot_name":"KIF1C","position":1033,"flank":"HPRRNSLDGGG","kinase":"","source":"hprd;pelm;psite","string_score":462},{"prot_id":"ENSP00000320821","prot_name":"KIF1C","position":1092,"flank":"MRRQRSAPDLK","kinase":"CSNK2A1","source":"hprd;pelm;psite","string_score":462},{"prot_id":"ENSP00000330572","prot_name":"MAPK8IP2","position":246,"flank":"GGRRSSQELSS","kinase":"","source":"psite","string_score":621},{"prot_id":"ENSP00000382423","prot_name":"MAP3K1","position":1016,"flank":"PCRIPSASPQT","kinase":"","source":"psite","string_score":907},{"prot_id":"ENSP00000382423","prot_name":"MAP3K1","position":1026,"flank":"TQRKFSLQFHR","kinase":"","source":"psite","string_score":907},{"prot_id":"ENSP00000343463","prot_name":"MAP3K2","position":163,"flank":"TSRDRSSPPPG","kinase":"","source":"hprd;pelm;psite","string_score":825},{"prot_id":"ENSP00000343463","prot_name":"MAP3K2","position":239,"flank":"MPRAQSYPDNH","kinase":"","source":"hprd;pelm;psite","string_score":825},{"prot_id":"ENSP00000343463","prot_name":"MAP3K2","position":331,"flank":"IRRRGSDIDNP","kinase":"","source":"hprd;pelm;psite","string_score":825},{"prot_id":"ENSP00000354927","prot_name":"MAP3K3","position":197,"flank":"RSRHLSVSSQN","kinase":"PRKACA","source":"hprd;pelm;psite","string_score":919},{"prot_id":"ENSP00000354927","prot_name":"MAP3K3","position":281,"flank":"MSRAQSFPDNR","kinase":"","source":"hprd;psite","string_score":919},{"prot_id":"ENSP00000354927","prot_name":"MAP3K3","position":347,"flank":"SSRSLSTNGEN","kinase":"","source":"psite","string_score":919},{"prot_id":"ENSP00000354927","prot_name":"MAP3K3","position":368,"flank":"RGRLRSADSEN","kinase":"PRKACA","source":"hprd;pelm;psite","string_score":919},{"prot_id":"ENSP00000354927","prot_name":"MAP3K3","position":547,"flank":"SKRLQTICMSG","kinase":"","source":"psite","string_score":919},{"prot_id":"ENSP00000354927","prot_name":"MAP3K3","position":559,"flank":"GMRSVTGTPYW","kinase":"","source":"psite","string_score":919},{"prot_id":"ENSP00000375986","prot_name":"MAP3K4","position":499,"flank":"LERLESEDDSL","kinase":"","source":"hprd;psite","string_score":969},{"prot_id":"ENSP00000350195","prot_name":"MAP3K6","position":964,"flank":"PKRCLSYGGTS","kinase":"","source":"hprd;psite","string_score":815},{"prot_id":"ENSP00000279488","prot_name":"DUSP6","position":174,"flank":"GLRISSDSSSD","kinase":"MAPK3","source":"psite","string_score":464},{"prot_id":"ENSP00000253055","prot_name":"MAP3K10","position":498,"flank":"DKRKGSDGASP","kinase":"","source":"psite","string_score":910},{"prot_id":"ENSP00000253055","prot_name":"MAP3K10","position":830,"flank":"HRRTPSDGALG","kinase":"","source":"psite","string_score":910},{"prot_id":"ENSP00000307235","prot_name":"EIF2AK3","position":555,"flank":"RQRKESETQCQ","kinase":"","source":"psite","string_score":813},{"prot_id":"ENSP00000307235","prot_name":"EIF2AK3","position":802,"flank":"RSRERTSSSIV","kinase":"","source":"psite","string_score":813},{"prot_id":"ENSP00000307235","prot_name":"EIF2AK3","position":804,"flank":"RERTSSSIVFE","kinase":"","source":"psite","string_score":813},{"prot_id":"ENSP00000307235","prot_name":"EIF2AK3","position":1094,"flank":"RQRSRSLSSSG","kinase":"","source":"psite","string_score":813},{"prot_id":"ENSP00000307235","prot_name":"EIF2AK3","position":1096,"flank":"RSRSLSSSGTK","kinase":"","source":"psite","string_score":813},{"prot_id":"ENSP00000343325","prot_name":"PKN1","position":69,"flank":"NLRRATTDLGR","kinase":"","source":"psite","string_score":962},{"prot_id":"ENSP00000343325","prot_name":"PKN1","position":70,"flank":"LRRATTDLGRS","kinase":"PKN1","source":"hprd;psite","string_score":962},{"prot_id":"ENSP00000343325","prot_name":"PKN1","position":246,"flank":"VLRLLSAAKAP","kinase":"","source":"hprd;psite","string_score":962},{"prot_id":"ENSP00000343325","prot_name":"PKN1","position":380,"flank":"YSRSGSLSGRS","kinase":"PKN1","source":"hprd;psite","string_score":962},{"prot_id":"ENSP00000343325","prot_name":"PKN1","position":780,"flank":"GDRTSTFCGTP","kinase":"PDK1;PDPK1;PKN1","source":"hprd;pelm;psite","string_score":962},{"prot_id":"ENSP00000260402","prot_name":"PLCB2","position":601,"flank":"NKRQMSRIYPK","kinase":"","source":"pelm;psite","string_score":921},{"prot_id":"ENSP00000012443","prot_name":"PPP5C","position":105,"flank":"YRRAASNMALG","kinase":"","source":"psite","string_score":460},{"prot_id":"ENSP00000348461","prot_name":"RAC1","position":71,"flank":"RLRPLSYPQTV","kinase":"AKT1","source":"hprd;psite","string_score":937},{"prot_id":"ENSP00000259808","prot_name":"RIPK1","position":320,"flank":"VKRMQSLQLDC","kinase":"","source":"hprd;pelm;psite","string_score":903},{"prot_id":"ENSP00000259808","prot_name":"RIPK1","position":416,"flank":"RRRRVSHDPFA","kinase":"","source":"psite","string_score":903},{"prot_id":"ENSP00000262158","prot_name":"SMAD7","position":121,"flank":"ESRGGTRTACL","kinase":"","source":"psite","string_score":793},{"prot_id":"ENSP00000286332","prot_name":"TAB2","position":423,"flank":"ASRNMSGQVSM","kinase":"","source":"psite","string_score":918},{"prot_id":"ENSP00000286332","prot_name":"TAB2","position":524,"flank":"ETRKLSMGSDD","kinase":"","source":"hprd;psite","string_score":918},{"prot_id":"ENSP00000286332","prot_name":"TAB2","position":582,"flank":"LKRSNSISQIP","kinase":"","source":"psite","string_score":918},{"prot_id":"ENSP00000358335","prot_name":"MAP3K7","position":439,"flank":"QPRRRSIQDLT","kinase":"","source":"hprd;pelm;psite","string_score":923},{"prot_id":"ENSP00000261716","prot_name":"TAOK1","position":9,"flank":"TNRAGSLKDPE","kinase":"","source":"hprd;pelm;psite","string_score":964},{"prot_id":"ENSP00000261716","prot_name":"TAOK1","position":445,"flank":"TIRTASLVTRQ","kinase":"","source":"hprd;pelm;psite","string_score":964},{"prot_id":"ENSP00000261716","prot_name":"TAOK1","position":974,"flank":"LRRTASGGRTE","kinase":"","source":"psite","string_score":964},{"prot_id":"ENSP00000261716","prot_name":"TAOK1","position":987,"flank":"MSRSTSVTSQI","kinase":"","source":"psite","string_score":964},{"prot_id":"ENSP00000310094","prot_name":"TAOK2","position":9,"flank":"GGRAGSLKDPD","kinase":"","source":"hprd;psite","string_score":985},{"prot_id":"ENSP00000310094","prot_name":"TAOK2","position":344,"flank":"MHRAGTLTSLE","kinase":"","source":"psite","string_score":985},{"prot_id":"ENSP00000310094","prot_name":"TAOK2","position":473,"flank":"TIRTASLVSRQ","kinase":"","source":"hprd;psite","string_score":985},{"prot_id":"ENSP00000376317","prot_name":"TAOK3","position":437,"flank":"RERFATIKSAS","kinase":"","source":"psite","string_score":901},{"prot_id":"ENSP00000162749","prot_name":"TNFRSF1A","position":417,"flank":"PRREATLELLG","kinase":"","source":"psite","string_score":917},{"prot_id":"ENSP00000341268","prot_name":"TRADD","position":215,"flank":"VNRPLSLKDQQ","kinase":"","source":"psite","string_score":914},{"prot_id":"ENSP00000344818","prot_name":"UBC","position":57,"flank":"DGRTLSDYNIQ","kinase":"","source":"hprd;psite","string_score":720},{"prot_id":"ENSP00000314709","prot_name":"ZHX2","position":713,"flank":"VARKATKPMAE","kinase":"","source":"psite","string_score":661},{"prot_id":"ENSP00000365439","prot_name":"HNRNPK","position":417,"flank":"QIRHESGASIK","kinase":"","source":"hprd","string_score":686},{"prot_id":"ENSP00000307235","prot_name":"EIF2AK3","position":862,"flank":"PPRPTTLSLDL","kinase":"","source":"hprd","string_score":813},{"prot_id":"ENSP00000261716","prot_name":"TAOK1","position":959,"flank":"VPRGSSMGVRN","kinase":"","source":"hprd","string_score":964}]
