[{"sub_ensp":"ENSP00000217971","sub_name":"PGRMC1","sub_position":181,"sub_region":"EPTVYSDEEEP","kinase_name":"","source":"psite;pelm;hprd","string_score":429},{"sub_ensp":"ENSP00000217971","sub_name":"PGRMC1","sub_position":57,"sub_region":"AASGDSDDDEP","kinase_name":"","source":"psite;pelm;hprd","string_score":429},{"sub_ensp":"ENSP00000222115","sub_name":"HAS1","sub_position":571,"sub_region":"LCRRRTGGYRV","kinase_name":"","source":"psite","string_score":491},{"sub_ensp":"ENSP00000222248","sub_name":"SLC5A5","sub_position":377,"sub_region":"KPRLRSLAPRK","kinase_name":"","source":"psite","string_score":508},{"sub_ensp":"ENSP00000225402","sub_name":"AATF","sub_position":143,"sub_region":"KSRSHSAKTPG","kinase_name":"CHEK2","source":"psite","string_score":657},{"sub_ensp":"ENSP00000225402","sub_name":"AATF","sub_position":153,"sub_region":"GFSVQSISDFE","kinase_name":"","source":"psite","string_score":657},{"sub_ensp":"ENSP00000225402","sub_name":"AATF","sub_position":155,"sub_region":"SVQSISDFEKF","kinase_name":"","source":"psite;pelm;hprd","string_score":657},{"sub_ensp":"ENSP00000225402","sub_name":"AATF","sub_position":366,"sub_region":"VYRNRTLQKWH","kinase_name":"","source":"psite","string_score":657},{"sub_ensp":"ENSP00000225402","sub_name":"AATF","sub_position":477,"sub_region":"IERKTSSLDPN","kinase_name":"CHEK2","source":"psite","string_score":657},{"sub_ensp":"ENSP00000225402","sub_name":"AATF","sub_position":510,"sub_region":"VDRKASKGRKL","kinase_name":"CHEK2","source":"psite","string_score":657},{"sub_ensp":"ENSP00000225402","sub_name":"AATF","sub_position":94,"sub_region":"TLPGSSDEEIS","kinase_name":"","source":"hprd","string_score":657},{"sub_ensp":"ENSP00000225402","sub_name":"AATF","sub_position":99,"sub_region":"SDEEISDEEGS","kinase_name":"","source":"hprd","string_score":657},{"sub_ensp":"ENSP00000229277","sub_name":"ENO2","sub_position":40,"sub_region":"VPSGASTGIYE","kinase_name":"","source":"psite","string_score":514},{"sub_ensp":"ENSP00000234590","sub_name":"ENO1","sub_position":40,"sub_region":"VPSGASTGIYE","kinase_name":"","source":"psite","string_score":562},{"sub_ensp":"ENSP00000245441","sub_name":"NIN","sub_position":1145,"sub_region":"RRHVLSDLEDD","kinase_name":"","source":"psite","string_score":609},{"sub_ensp":"ENSP00000245441","sub_name":"NIN","sub_position":1927,"sub_region":"ANRKVSQMNSL","kinase_name":"","source":"psite","string_score":609},{"sub_ensp":"ENSP00000245441","sub_name":"NIN","sub_position":269,"sub_region":"LKRHLSMQSFD","kinase_name":"","source":"psite","string_score":609},{"sub_ensp":"ENSP00000250454","sub_name":"EAPP","sub_position":109,"sub_region":"DIYFDSDSEDE","kinase_name":"","source":"psite;pelm;hprd","string_score":412},{"sub_ensp":"ENSP00000250454","sub_name":"EAPP","sub_position":17,"sub_region":"AVEEPSDEEPA","kinase_name":"","source":"psite;pelm;hprd","string_score":412},{"sub_ensp":"ENSP00000250454","sub_name":"EAPP","sub_position":56,"sub_region":"GESESSSEDEF","kinase_name":"","source":"psite;hprd","string_score":412},{"sub_ensp":"ENSP00000250454","sub_name":"EAPP","sub_position":85,"sub_region":"LSSLGTGSSSG","kinase_name":"","source":"hprd","string_score":412},{"sub_ensp":"ENSP00000257745","sub_name":"KMT2E","sub_position":623,"sub_region":"DTQIVSDAEVI","kinase_name":"","source":"psite","string_score":900},{"sub_ensp":"ENSP00000262630","sub_name":"ZBTB32","sub_position":396,"sub_region":"HYRVHTGEKPF","kinase_name":"","source":"psite","string_score":540},{"sub_ensp":"ENSP00000262809","sub_name":"ELL","sub_position":145,"sub_region":"ETRSRSAIVIK","kinase_name":"","source":"hprd","string_score":543},{"sub_ensp":"ENSP00000262809","sub_name":"ELL","sub_position":194,"sub_region":"RKSGASAVSGG","kinase_name":"","source":"psite","string_score":543},{"sub_ensp":"ENSP00000262809","sub_name":"ELL","sub_position":200,"sub_region":"AVSGGSGVSQR","kinase_name":"","source":"psite","string_score":543},{"sub_ensp":"ENSP00000262809","sub_name":"ELL","sub_position":203,"sub_region":"GGSGVSQRPFR","kinase_name":"","source":"psite","string_score":543},{"sub_ensp":"ENSP00000262809","sub_name":"ELL","sub_position":561,"sub_region":"QLRQLSQGSEE","kinase_name":"","source":"psite;pelm;hprd","string_score":543},{"sub_ensp":"ENSP00000262965","sub_name":"TCF3","sub_position":354,"sub_region":"FSSSPSTPVGS","kinase_name":"","source":"psite","string_score":422},{"sub_ensp":"ENSP00000262965","sub_name":"TCF3","sub_position":39,"sub_region":"KGRPASLAGAQ","kinase_name":"","source":"psite","string_score":422},{"sub_ensp":"ENSP00000263360","sub_name":"EED","sub_position":46,"sub_region":"AVSIESGTNTE","kinase_name":"","source":"hprd","string_score":739},{"sub_ensp":"ENSP00000264162","sub_name":"LCT","sub_position":324,"sub_region":"FLSCSSSSKKS","kinase_name":"","source":"psite","string_score":412},{"sub_ensp":"ENSP00000264162","sub_name":"LCT","sub_position":326,"sub_region":"SCSSSSKKSMS","kinase_name":"","source":"psite","string_score":412},{"sub_ensp":"ENSP00000265960","sub_name":"MAPKAP1","sub_position":510,"sub_region":"LNRRTSFSFQK","kinase_name":"","source":"psite;pelm;hprd","string_score":620},{"sub_ensp":"ENSP00000265960","sub_name":"MAPKAP1","sub_position":84,"sub_region":"GIRRRSNTAQR","kinase_name":"","source":"psite","string_score":620},{"sub_ensp":"ENSP00000265960","sub_name":"MAPKAP1","sub_position":86,"sub_region":"RRRSNTAQRLE","kinase_name":"","source":"psite","string_score":620},{"sub_ensp":"ENSP00000278823","sub_name":"MTA2","sub_position":438,"sub_region":"SLSPYTTSANR","kinase_name":"CDK2","source":"psite;pelm","string_score":430},{"sub_ensp":"ENSP00000278823","sub_name":"MTA2","sub_position":52,"sub_region":"RRRDISSSLNS","kinase_name":"","source":"psite","string_score":430},{"sub_ensp":"ENSP00000278823","sub_name":"MTA2","sub_position":57,"sub_region":"SSSLNSLADSN","kinase_name":"","source":"pelm;hprd","string_score":430},{"sub_ensp":"ENSP00000278823","sub_name":"MTA2","sub_position":587,"sub_region":"GIRSSSQPAAK","kinase_name":"","source":"psite","string_score":430},{"sub_ensp":"ENSP00000292476","sub_name":"CPSF4","sub_position":202,"sub_region":"LQRSSSLIQLT","kinase_name":"","source":"psite;pelm;hprd","string_score":504},{"sub_ensp":"ENSP00000292476","sub_name":"CPSF4","sub_position":211,"sub_region":"LTSQNSSPNQQ","kinase_name":"","source":"psite","string_score":504},{"sub_ensp":"ENSP00000292476","sub_name":"CPSF4","sub_position":61,"sub_region":"PFRHISGEKTV","kinase_name":"","source":"psite","string_score":504},{"sub_ensp":"ENSP00000296456","sub_name":"APEH","sub_position":187,"sub_region":"LDVSASDDEIA","kinase_name":"","source":"psite;pelm;hprd","string_score":432},{"sub_ensp":"ENSP00000297848","sub_name":"COL14A1","sub_position":989,"sub_region":"KISVYTKLQEI","kinase_name":"","source":"psite;hprd","string_score":671},{"sub_ensp":"ENSP00000298687","sub_name":"NDRG2","sub_position":323,"sub_region":"ASSCMTRLSRS","kinase_name":"","source":"psite","string_score":861},{"sub_ensp":"ENSP00000298687","sub_name":"NDRG2","sub_position":330,"sub_region":"LSRSRTASLTS","kinase_name":"SGK1","source":"psite;pelm;hprd","string_score":861},{"sub_ensp":"ENSP00000298687","sub_name":"NDRG2","sub_position":332,"sub_region":"RSRTASLTSAA","kinase_name":"AKT1;RPS6KA1;RPS6KB1;SGK1","source":"psite;pelm;hprd","string_score":861},{"sub_ensp":"ENSP00000298687","sub_name":"NDRG2","sub_position":335,"sub_region":"TASLTSAASVD","kinase_name":"","source":"psite;hprd","string_score":861},{"sub_ensp":"ENSP00000298687","sub_name":"NDRG2","sub_position":338,"sub_region":"LTSAASVDGNR","kinase_name":"","source":"psite;pelm;hprd","string_score":861},{"sub_ensp":"ENSP00000298687","sub_name":"NDRG2","sub_position":346,"sub_region":"GNRSRSRTLSQ","kinase_name":"SGK1","source":"psite;pelm;hprd","string_score":861},{"sub_ensp":"ENSP00000298687","sub_name":"NDRG2","sub_position":348,"sub_region":"RSRSRTLSQSS","kinase_name":"AKT1;SGK1","source":"psite;pelm;hprd","string_score":861},{"sub_ensp":"ENSP00000298687","sub_name":"NDRG2","sub_position":350,"sub_region":"RSRTLSQSSES","kinase_name":"RPS6KA1;RPS6KB1","source":"psite;pelm;hprd","string_score":861},{"sub_ensp":"ENSP00000298687","sub_name":"NDRG2","sub_position":353,"sub_region":"TLSQSSESGTL","kinase_name":"","source":"psite;pelm;hprd","string_score":861},{"sub_ensp":"ENSP00000298687","sub_name":"NDRG2","sub_position":355,"sub_region":"SQSSESGTLSS","kinase_name":"","source":"psite;hprd","string_score":861},{"sub_ensp":"ENSP00000299543","sub_name":"CTDP1","sub_position":338,"sub_region":"PGSRESQTRKK","kinase_name":"","source":"psite","string_score":621},{"sub_ensp":"ENSP00000299543","sub_name":"CTDP1","sub_position":474,"sub_region":"SSSSASDGESE","kinase_name":"","source":"psite","string_score":621},{"sub_ensp":"ENSP00000299543","sub_name":"CTDP1","sub_position":839,"sub_region":"RKRQPSMSETM","kinase_name":"","source":"psite","string_score":621},{"sub_ensp":"ENSP00000299543","sub_name":"CTDP1","sub_position":872,"sub_region":"EGSDDSDSEKR","kinase_name":"","source":"psite;pelm;hprd","string_score":621},{"sub_ensp":"ENSP00000299543","sub_name":"CTDP1","sub_position":935,"sub_region":"ESSRESSNEDE","kinase_name":"","source":"psite","string_score":621},{"sub_ensp":"ENSP00000299543","sub_name":"CTDP1","sub_position":936,"sub_region":"SSRESSNEDEG","kinase_name":"","source":"psite","string_score":621},{"sub_ensp":"ENSP00000300055","sub_name":"PLIN1","sub_position":299,"sub_region":"DHEDQTDTEGE","kinase_name":"","source":"psite","string_score":427},{"sub_ensp":"ENSP00000300055","sub_name":"PLIN1","sub_position":382,"sub_region":"KGRAMSLSDAL","kinase_name":"","source":"psite","string_score":427},{"sub_ensp":"ENSP00000300055","sub_name":"PLIN1","sub_position":497,"sub_region":"PKRRVSDSFFR","kinase_name":"","source":"psite","string_score":427},{"sub_ensp":"ENSP00000300055","sub_name":"PLIN1","sub_position":81,"sub_region":"VVRRLSTQFTA","kinase_name":"PRKACA","source":"psite;hprd","string_score":427},{"sub_ensp":"ENSP00000301764","sub_name":"DDB1","sub_position":1125,"sub_region":"MKREATADDLI","kinase_name":"","source":"psite","string_score":462},{"sub_ensp":"ENSP00000301764","sub_name":"DDB1","sub_position":645,"sub_region":"TFRSLSTTNVF","kinase_name":"","source":"psite","string_score":462},{"sub_ensp":"ENSP00000301764","sub_name":"DDB1","sub_position":646,"sub_region":"FRSLSTTNVFA","kinase_name":"","source":"psite","string_score":462},{"sub_ensp":"ENSP00000302051","sub_name":"ECEL1","sub_position":32,"sub_region":"GARGASLPPGF","kinase_name":"","source":"psite","string_score":412},{"sub_ensp":"ENSP00000304467","sub_name":"THOP1","sub_position":19,"sub_region":"AASPCSVVNDL","kinase_name":"","source":"psite","string_score":501},{"sub_ensp":"ENSP00000306185","sub_name":"ANTXR2","sub_position":90,"sub_region":"FSSQATIILPL","kinase_name":"","source":"hprd","string_score":434},{"sub_ensp":"ENSP00000308928","sub_name":"CYLD","sub_position":418,"sub_region":"ENRFHSLPFSL","kinase_name":"IKBKB","source":"psite","string_score":468},{"sub_ensp":"ENSP00000308928","sub_name":"CYLD","sub_position":439,"sub_region":"GHSPLSLSAQS","kinase_name":"IKBKB","source":"psite","string_score":468},{"sub_ensp":"ENSP00000308928","sub_name":"CYLD","sub_position":444,"sub_region":"SLSAQSVMEEL","kinase_name":"IKBKB","source":"psite","string_score":468},{"sub_ensp":"ENSP00000308928","sub_name":"CYLD","sub_position":547,"sub_region":"DSRFASLQPVS","kinase_name":"","source":"psite","string_score":468},{"sub_ensp":"ENSP00000309555","sub_name":"HCFC1","sub_position":1224,"sub_region":"RLSSPSIKDLP","kinase_name":"","source":"psite;hprd","string_score":900},{"sub_ensp":"ENSP00000309555","sub_name":"HCFC1","sub_position":2007,"sub_region":"ETSKDSSGTKP","kinase_name":"","source":"hprd","string_score":900},{"sub_ensp":"ENSP00000309555","sub_name":"HCFC1","sub_position":2019,"sub_region":"NKRPMSSPEMK","kinase_name":"","source":"psite;hprd","string_score":900},{"sub_ensp":"ENSP00000309555","sub_name":"HCFC1","sub_position":377,"sub_region":"LVRANTNSLEV","kinase_name":"","source":"psite;hprd","string_score":900},{"sub_ensp":"ENSP00000309555","sub_name":"HCFC1","sub_position":507,"sub_region":"TMRPASQAGKA","kinase_name":"","source":"psite","string_score":900},{"sub_ensp":"ENSP00000309555","sub_name":"HCFC1","sub_position":669,"sub_region":"VKSPISVPGGS","kinase_name":"","source":"psite;pelm;hprd","string_score":900},{"sub_ensp":"ENSP00000309555","sub_name":"HCFC1","sub_position":797,"sub_region":"IKSPITIITTK","kinase_name":"","source":"psite","string_score":900},{"sub_ensp":"ENSP00000310189","sub_name":"MOB1B","sub_position":12,"sub_region":"SRSSKTFKPKK","kinase_name":"STK3;STK4","source":"psite","string_score":430},{"sub_ensp":"ENSP00000311596","sub_name":"ZNF699","sub_position":131,"sub_region":"FKRNDSWFSSL","kinase_name":"","source":"psite","string_score":530},{"sub_ensp":"ENSP00000311596","sub_name":"ZNF699","sub_position":526,"sub_region":"HIRTHTGEKPY","kinase_name":"","source":"psite","string_score":530},{"sub_ensp":"ENSP00000311596","sub_name":"ZNF699","sub_position":554,"sub_region":"HMRTHTGEKPY","kinase_name":"","source":"psite","string_score":530},{"sub_ensp":"ENSP00000312288","sub_name":"HADH","sub_position":16,"sub_region":"SVSSSSTASAS","kinase_name":"","source":"hprd","string_score":611},{"sub_ensp":"ENSP00000312288","sub_name":"HADH","sub_position":17,"sub_region":"VSSSSTASASA","kinase_name":"","source":"hprd","string_score":611},{"sub_ensp":"ENSP00000312288","sub_name":"HADH","sub_position":19,"sub_region":"SSSTASASAKK","kinase_name":"","source":"hprd","string_score":611},{"sub_ensp":"ENSP00000315569","sub_name":"DIS3L2","sub_position":173,"sub_region":"AQFDGSDSEDG","kinase_name":"","source":"psite","string_score":400},{"sub_ensp":"ENSP00000315569","sub_name":"DIS3L2","sub_position":875,"sub_region":"KEEEESDGEPE","kinase_name":"","source":"psite;hprd","string_score":400},{"sub_ensp":"ENSP00000315702","sub_name":"MOB4","sub_position":147,"sub_region":"FPSRVSIKESS","kinase_name":"","source":"psite","string_score":831},{"sub_ensp":"ENSP00000319977","sub_name":"NDRG1","sub_position":328,"sub_region":"LMRSRTASGSS","kinase_name":"SGK1","source":"psite;pelm;hprd","string_score":792},{"sub_ensp":"ENSP00000319977","sub_name":"NDRG1","sub_position":330,"sub_region":"RSRTASGSSVT","kinase_name":"PRKACA;SGK1","source":"psite;pelm;hprd","string_score":792},{"sub_ensp":"ENSP00000319977","sub_name":"NDRG1","sub_position":333,"sub_region":"TASGSSVTSLD","kinase_name":"","source":"psite;pelm;hprd","string_score":792},{"sub_ensp":"ENSP00000319977","sub_name":"NDRG1","sub_position":335,"sub_region":"SGSSVTSLDGT","kinase_name":"","source":"psite;pelm;hprd","string_score":792},{"sub_ensp":"ENSP00000319977","sub_name":"NDRG1","sub_position":336,"sub_region":"GSSVTSLDGTR","kinase_name":"","source":"psite;pelm;hprd","string_score":792},{"sub_ensp":"ENSP00000319977","sub_name":"NDRG1","sub_position":344,"sub_region":"GTRSRSHTSEG","kinase_name":"","source":"psite","string_score":792},{"sub_ensp":"ENSP00000319977","sub_name":"NDRG1","sub_position":346,"sub_region":"RSRSHTSEGTR","kinase_name":"SGK1","source":"psite;pelm","string_score":792},{"sub_ensp":"ENSP00000319977","sub_name":"NDRG1","sub_position":347,"sub_region":"SRSHTSEGTRS","kinase_name":"","source":"psite","string_score":792},{"sub_ensp":"ENSP00000319977","sub_name":"NDRG1","sub_position":350,"sub_region":"HTSEGTRSRSH","kinase_name":"","source":"psite","string_score":792},{"sub_ensp":"ENSP00000319977","sub_name":"NDRG1","sub_position":354,"sub_region":"GTRSRSHTSEG","kinase_name":"","source":"psite","string_score":792},{"sub_ensp":"ENSP00000319977","sub_name":"NDRG1","sub_position":364,"sub_region":"GTRSRSHTSEG","kinase_name":"","source":"psite;pelm;hprd","string_score":792},{"sub_ensp":"ENSP00000319977","sub_name":"NDRG1","sub_position":366,"sub_region":"RSRSHTSEGAH","kinase_name":"PRKACA;SGK1","source":"psite;pelm;hprd","string_score":792},{"sub_ensp":"ENSP00000319977","sub_name":"NDRG1","sub_position":367,"sub_region":"SRSHTSEGAHL","kinase_name":"","source":"psite;pelm;hprd","string_score":792},{"sub_ensp":"ENSP00000329448","sub_name":"NUTM1","sub_position":1029,"sub_region":"LASKLSLSPRE","kinase_name":"","source":"psite","string_score":514},{"sub_ensp":"ENSP00000337761","sub_name":"RAB27A","sub_position":83,"sub_region":"QERFRSLTTAF","kinase_name":"","source":"psite","string_score":534},{"sub_ensp":"ENSP00000345292","sub_name":"NDRG3","sub_position":329,"sub_region":"LARSRTHSTSS","kinase_name":"","source":"psite;pelm;hprd","string_score":861},{"sub_ensp":"ENSP00000345292","sub_name":"NDRG3","sub_position":331,"sub_region":"RSRTHSTSSSL","kinase_name":"","source":"psite;pelm;hprd","string_score":861},{"sub_ensp":"ENSP00000345292","sub_name":"NDRG3","sub_position":334,"sub_region":"THSTSSSLGSG","kinase_name":"","source":"psite;pelm;hprd","string_score":861},{"sub_ensp":"ENSP00000345292","sub_name":"NDRG3","sub_position":338,"sub_region":"SSSLGSGESPF","kinase_name":"","source":"psite;pelm;hprd","string_score":861},{"sub_ensp":"ENSP00000345292","sub_name":"NDRG3","sub_position":344,"sub_region":"GESPFSRSVTS","kinase_name":"","source":"psite","string_score":861},{"sub_ensp":"ENSP00000345292","sub_name":"NDRG3","sub_position":348,"sub_region":"FSRSVTSNQSD","kinase_name":"","source":"psite;hprd","string_score":861},{"sub_ensp":"ENSP00000345292","sub_name":"NDRG3","sub_position":349,"sub_region":"SRSVTSNQSDG","kinase_name":"","source":"psite","string_score":861},{"sub_ensp":"ENSP00000345292","sub_name":"NDRG3","sub_position":352,"sub_region":"VTSNQSDGTQE","kinase_name":"","source":"psite;pelm;hprd","string_score":861},{"sub_ensp":"ENSP00000345292","sub_name":"NDRG3","sub_position":355,"sub_region":"NQSDGTQESCE","kinase_name":"","source":"psite;hprd","string_score":861},{"sub_ensp":"ENSP00000345292","sub_name":"NDRG3","sub_position":370,"sub_region":"LDRHQTMEVSC","kinase_name":"","source":"psite","string_score":861},{"sub_ensp":"ENSP00000345689","sub_name":"RAB5C","sub_position":85,"sub_region":"QERYHSLAPMY","kinase_name":"","source":"psite","string_score":513},{"sub_ensp":"ENSP00000347942","sub_name":"RET","sub_position":696,"sub_region":"GARRPSLDSME","kinase_name":"PRKACA","source":"psite;pelm","string_score":430},{"sub_ensp":"ENSP00000348307","sub_name":"SIRPA","sub_position":467,"sub_region":"PASEDTLTYAD","kinase_name":"","source":"psite","string_score":497},{"sub_ensp":"ENSP00000348984","sub_name":"SON","sub_position":1035,"sub_region":"ERSMMSAYERS","kinase_name":"","source":"psite","string_score":565},{"sub_ensp":"ENSP00000348984","sub_name":"SON","sub_position":1043,"sub_region":"ERSMMSAYERS","kinase_name":"","source":"psite;hprd","string_score":565},{"sub_ensp":"ENSP00000348984","sub_name":"SON","sub_position":1097,"sub_region":"MMSSYSAADRS","kinase_name":"","source":"psite","string_score":565},{"sub_ensp":"ENSP00000348984","sub_name":"SON","sub_position":1651,"sub_region":"SPSGGSEADIE","kinase_name":"","source":"psite;pelm;hprd","string_score":565},{"sub_ensp":"ENSP00000348984","sub_name":"SON","sub_position":1747,"sub_region":"MERLTSLRAGI","kinase_name":"","source":"psite","string_score":565},{"sub_ensp":"ENSP00000348984","sub_name":"SON","sub_position":1766,"sub_region":"VGRDRSAASPV","kinase_name":"","source":"psite;pelm;hprd","string_score":565},{"sub_ensp":"ENSP00000348984","sub_name":"SON","sub_position":1783,"sub_region":"RASESSSEEKD","kinase_name":"","source":"psite;pelm;hprd","string_score":565},{"sub_ensp":"ENSP00000348984","sub_name":"SON","sub_position":1821,"sub_region":"KKRDSSLRSRS","kinase_name":"","source":"psite;hprd","string_score":565},{"sub_ensp":"ENSP00000348984","sub_name":"SON","sub_position":1824,"sub_region":"DSSLRSRSKRS","kinase_name":"","source":"psite;hprd","string_score":565},{"sub_ensp":"ENSP00000348984","sub_name":"SON","sub_position":1922,"sub_region":"TVRARSRTPSR","kinase_name":"","source":"psite;pelm;hprd","string_score":565},{"sub_ensp":"ENSP00000348984","sub_name":"SON","sub_position":1926,"sub_region":"RSRTPSRRSRS","kinase_name":"","source":"psite;hprd","string_score":565},{"sub_ensp":"ENSP00000348984","sub_name":"SON","sub_position":1929,"sub_region":"TPSRRSRSHTP","kinase_name":"","source":"psite","string_score":565},{"sub_ensp":"ENSP00000348984","sub_name":"SON","sub_position":1931,"sub_region":"SRRSRSHTPSR","kinase_name":"","source":"psite","string_score":565},{"sub_ensp":"ENSP00000348984","sub_name":"SON","sub_position":1940,"sub_region":"SRRRRSRSVGR","kinase_name":"","source":"psite","string_score":565},{"sub_ensp":"ENSP00000348984","sub_name":"SON","sub_position":1942,"sub_region":"RRRSRSVGRRR","kinase_name":"","source":"psite","string_score":565},{"sub_ensp":"ENSP00000348984","sub_name":"SON","sub_position":1948,"sub_region":"VGRRRSFSISP","kinase_name":"","source":"psite;pelm;hprd","string_score":565},{"sub_ensp":"ENSP00000348984","sub_name":"SON","sub_position":1950,"sub_region":"RRRSFSISPSR","kinase_name":"","source":"psite;pelm;hprd","string_score":565},{"sub_ensp":"ENSP00000348984","sub_name":"SON","sub_position":1957,"sub_region":"SPSRRSRTPSR","kinase_name":"","source":"psite","string_score":565},{"sub_ensp":"ENSP00000348984","sub_name":"SON","sub_position":1961,"sub_region":"RSRTPSRRSRT","kinase_name":"","source":"psite","string_score":565},{"sub_ensp":"ENSP00000348984","sub_name":"SON","sub_position":1964,"sub_region":"TPSRRSRTPSR","kinase_name":"","source":"psite","string_score":565},{"sub_ensp":"ENSP00000348984","sub_name":"SON","sub_position":1992,"sub_region":"TPSRRSRTPSR","kinase_name":"","source":"psite","string_score":565},{"sub_ensp":"ENSP00000348984","sub_name":"SON","sub_position":2001,"sub_region":"SRRRRSRSVVR","kinase_name":"","source":"psite;hprd","string_score":565},{"sub_ensp":"ENSP00000348984","sub_name":"SON","sub_position":2003,"sub_region":"RRRSRSVVRRR","kinase_name":"","source":"psite;hprd","string_score":565},{"sub_ensp":"ENSP00000348984","sub_name":"SON","sub_position":2009,"sub_region":"VVRRRSFSISP","kinase_name":"","source":"psite;pelm;hprd","string_score":565},{"sub_ensp":"ENSP00000348984","sub_name":"SON","sub_position":2011,"sub_region":"RRRSFSISPVR","kinase_name":"","source":"psite;pelm;hprd","string_score":565},{"sub_ensp":"ENSP00000348984","sub_name":"SON","sub_position":2029,"sub_region":"LRRRFSRSPIR","kinase_name":"","source":"psite;pelm;hprd","string_score":565},{"sub_ensp":"ENSP00000348984","sub_name":"SON","sub_position":2129,"sub_region":"NKPHVSDEEEE","kinase_name":"","source":"psite;pelm;hprd","string_score":565},{"sub_ensp":"ENSP00000348984","sub_name":"SON","sub_position":2181,"sub_region":"PVSSGSQHRKK","kinase_name":"","source":"psite;hprd","string_score":565},{"sub_ensp":"ENSP00000348984","sub_name":"SON","sub_position":55,"sub_region":"AASARSLPNEE","kinase_name":"","source":"psite","string_score":565},{"sub_ensp":"ENSP00000348984","sub_name":"SON","sub_position":94,"sub_region":"KSRCVSVQTDP","kinase_name":"","source":"psite;pelm;hprd","string_score":565},{"sub_ensp":"ENSP00000348984","sub_name":"SON","sub_position":998,"sub_region":"LASRRSMMMSY","kinase_name":"","source":"psite","string_score":565},{"sub_ensp":"ENSP00000349486","sub_name":"SCRIB","sub_position":1223,"sub_region":"RNSLESISSID","kinase_name":"","source":"psite;pelm;hprd","string_score":430},{"sub_ensp":"ENSP00000349486","sub_name":"SCRIB","sub_position":1226,"sub_region":"LESISSIDREL","kinase_name":"","source":"psite;pelm;hprd","string_score":430},{"sub_ensp":"ENSP00000349486","sub_name":"SCRIB","sub_position":1279,"sub_region":"VPSAGSVQRVP","kinase_name":"","source":"psite","string_score":430},{"sub_ensp":"ENSP00000349486","sub_name":"SCRIB","sub_position":1285,"sub_region":"VQRVPSGAAGG","kinase_name":"","source":"psite","string_score":430},{"sub_ensp":"ENSP00000349486","sub_name":"SCRIB","sub_position":1442,"sub_region":"SPSPTSRQSPA","kinase_name":"","source":"psite;pelm;hprd","string_score":430},{"sub_ensp":"ENSP00000349486","sub_name":"SCRIB","sub_position":1508,"sub_region":"AARMKSLEQDA","kinase_name":"","source":"psite;pelm;hprd","string_score":430},{"sub_ensp":"ENSP00000349486","sub_name":"SCRIB","sub_position":703,"sub_region":"VVSAPSVKGVS","kinase_name":"","source":"psite","string_score":430},{"sub_ensp":"ENSP00000349959","sub_name":"RICTOR","sub_position":1026,"sub_region":"TLSLNSESTSS","kinase_name":"","source":"psite","string_score":635},{"sub_ensp":"ENSP00000349959","sub_name":"RICTOR","sub_position":1031,"sub_region":"SESTSSRHNSE","kinase_name":"","source":"psite","string_score":635},{"sub_ensp":"ENSP00000349959","sub_name":"RICTOR","sub_position":1035,"sub_region":"SSRHNSESESV","kinase_name":"","source":"psite","string_score":635},{"sub_ensp":"ENSP00000349959","sub_name":"RICTOR","sub_position":1133,"sub_region":"NRRIRTLTEPS","kinase_name":"","source":"psite","string_score":635},{"sub_ensp":"ENSP00000349959","sub_name":"RICTOR","sub_position":1135,"sub_region":"RIRTLTEPSVD","kinase_name":"AKT1;RPS6KB1;RPS6KB2;SGK1","source":"psite","string_score":635},{"sub_ensp":"ENSP00000349959","sub_name":"RICTOR","sub_position":1177,"sub_region":"TGSTPSIGEND","kinase_name":"","source":"psite;pelm","string_score":635},{"sub_ensp":"ENSP00000349959","sub_name":"RICTOR","sub_position":1219,"sub_region":"KIRSQSFNTDT","kinase_name":"","source":"psite;hprd","string_score":635},{"sub_ensp":"ENSP00000349959","sub_name":"RICTOR","sub_position":1222,"sub_region":"SQSFNTDTTTS","kinase_name":"","source":"psite;hprd","string_score":635},{"sub_ensp":"ENSP00000349959","sub_name":"RICTOR","sub_position":1230,"sub_region":"TTSGISSMSSS","kinase_name":"","source":"psite","string_score":635},{"sub_ensp":"ENSP00000349959","sub_name":"RICTOR","sub_position":1295,"sub_region":"PGSSHTLPRRA","kinase_name":"","source":"psite;hprd","string_score":635},{"sub_ensp":"ENSP00000349959","sub_name":"RICTOR","sub_position":1302,"sub_region":"PRRAQSLKAPS","kinase_name":"","source":"psite","string_score":635},{"sub_ensp":"ENSP00000349959","sub_name":"RICTOR","sub_position":1388,"sub_region":"ALSYASLDKED","kinase_name":"","source":"psite;hprd","string_score":635},{"sub_ensp":"ENSP00000349959","sub_name":"RICTOR","sub_position":1411,"sub_region":"SSSVRSMVSSA","kinase_name":"","source":"psite","string_score":635},{"sub_ensp":"ENSP00000349959","sub_name":"RICTOR","sub_position":1414,"sub_region":"VRSMVSSATYG","kinase_name":"","source":"psite","string_score":635},{"sub_ensp":"ENSP00000349959","sub_name":"RICTOR","sub_position":1417,"sub_region":"MVSSATYGGSD","kinase_name":"","source":"psite","string_score":635},{"sub_ensp":"ENSP00000349959","sub_name":"RICTOR","sub_position":1571,"sub_region":"VPSKFSGISGC","kinase_name":"","source":"psite","string_score":635},{"sub_ensp":"ENSP00000349959","sub_name":"RICTOR","sub_position":1574,"sub_region":"KFSGISGCSDG","kinase_name":"","source":"psite","string_score":635},{"sub_ensp":"ENSP00000349959","sub_name":"RICTOR","sub_position":1577,"sub_region":"GISGCSDGVSQ","kinase_name":"","source":"psite","string_score":635},{"sub_ensp":"ENSP00000349959","sub_name":"RICTOR","sub_position":1591,"sub_region":"ASSTKSTELLL","kinase_name":"","source":"psite;hprd","string_score":635},{"sub_ensp":"ENSP00000349959","sub_name":"RICTOR","sub_position":21,"sub_region":"RGRNDSGEENV","kinase_name":"","source":"psite;pelm;hprd","string_score":635},{"sub_ensp":"ENSP00000349959","sub_name":"RICTOR","sub_position":35,"sub_region":"LTREPSDNLRE","kinase_name":"","source":"psite","string_score":635},{"sub_ensp":"ENSP00000349959","sub_name":"RICTOR","sub_position":383,"sub_region":"PHRARSRPDLM","kinase_name":"","source":"psite","string_score":635},{"sub_ensp":"ENSP00000349960","sub_name":"ACTB","sub_position":186,"sub_region":"AGRDLTDYLMK","kinase_name":"","source":"psite","string_score":904},{"sub_ensp":"ENSP00000349960","sub_name":"ACTB","sub_position":199,"sub_region":"TERGYSFTTTA","kinase_name":"","source":"psite","string_score":904},{"sub_ensp":"ENSP00000349960","sub_name":"ACTB","sub_position":202,"sub_region":"GYSFTTTAERE","kinase_name":"","source":"psite","string_score":904},{"sub_ensp":"ENSP00000349960","sub_name":"ACTB","sub_position":303,"sub_region":"VLSGGTTMYPG","kinase_name":"","source":"psite","string_score":904},{"sub_ensp":"ENSP00000349960","sub_name":"ACTB","sub_position":368,"sub_region":"DESGPSIVHRK","kinase_name":"","source":"psite","string_score":904},{"sub_ensp":"ENSP00000351113","sub_name":"FRYL","sub_position":101,"sub_region":"RPRSSTKSKGD","kinase_name":"","source":"psite","string_score":443},{"sub_ensp":"ENSP00000351113","sub_name":"FRYL","sub_position":1539,"sub_region":"SSSGGSYEEEK","kinase_name":"","source":"psite","string_score":443},{"sub_ensp":"ENSP00000351113","sub_name":"FRYL","sub_position":1898,"sub_region":"ALSQTSYHDPI","kinase_name":"","source":"psite","string_score":443},{"sub_ensp":"ENSP00000351113","sub_name":"FRYL","sub_position":1915,"sub_region":"ANRKSTGQLNL","kinase_name":"","source":"psite","string_score":443},{"sub_ensp":"ENSP00000351113","sub_name":"FRYL","sub_position":1941,"sub_region":"NARSNSLRLSL","kinase_name":"","source":"psite","string_score":443},{"sub_ensp":"ENSP00000351113","sub_name":"FRYL","sub_position":1957,"sub_region":"GDRRRSNTLDI","kinase_name":"","source":"psite","string_score":443},{"sub_ensp":"ENSP00000351113","sub_name":"FRYL","sub_position":1959,"sub_region":"RRRSNTLDIMD","kinase_name":"","source":"psite;pelm","string_score":443},{"sub_ensp":"ENSP00000351113","sub_name":"FRYL","sub_position":1978,"sub_region":"LARTRSLSSLR","kinase_name":"","source":"psite;hprd","string_score":443},{"sub_ensp":"ENSP00000351113","sub_name":"FRYL","sub_position":2332,"sub_region":"VTRSTSSTSSG","kinase_name":"","source":"psite","string_score":443},{"sub_ensp":"ENSP00000351113","sub_name":"FRYL","sub_position":2333,"sub_region":"TRSTSSTSSGS","kinase_name":"","source":"pelm","string_score":443},{"sub_ensp":"ENSP00000351113","sub_name":"FRYL","sub_position":2335,"sub_region":"STSSTSSGSNS","kinase_name":"","source":"psite","string_score":443},{"sub_ensp":"ENSP00000351113","sub_name":"FRYL","sub_position":2454,"sub_region":"GVRRRSLDSID","kinase_name":"","source":"psite","string_score":443},{"sub_ensp":"ENSP00000351113","sub_name":"FRYL","sub_position":2457,"sub_region":"RRSLDSIDKGD","kinase_name":"","source":"psite","string_score":443},{"sub_ensp":"ENSP00000351113","sub_name":"FRYL","sub_position":482,"sub_region":"LPSGNTLRVKK","kinase_name":"","source":"psite","string_score":443},{"sub_ensp":"ENSP00000351113","sub_name":"FRYL","sub_position":807,"sub_region":"IISLSSFLKQE","kinase_name":"","source":"psite;hprd","string_score":443},{"sub_ensp":"ENSP00000352673","sub_name":"ELF3","sub_position":207,"sub_region":"GASRSSHSSDS","kinase_name":"PAK1","source":"psite","string_score":563},{"sub_ensp":"ENSP00000352673","sub_name":"ELF3","sub_position":212,"sub_region":"SHSSDSGGSDV","kinase_name":"","source":"pelm;hprd","string_score":563},{"sub_ensp":"ENSP00000352673","sub_name":"ELF3","sub_position":215,"sub_region":"SDSGGSDVDLD","kinase_name":"","source":"pelm;hprd","string_score":563},{"sub_ensp":"ENSP00000354558","sub_name":"MTOR","sub_position":1418,"sub_region":"LESLISINNKL","kinase_name":"","source":"psite","string_score":627},{"sub_ensp":"ENSP00000354558","sub_name":"MTOR","sub_position":1821,"sub_region":"KLRHASGANIT","kinase_name":"","source":"psite","string_score":627},{"sub_ensp":"ENSP00000354558","sub_name":"MTOR","sub_position":2444,"sub_region":"NKRSRTRTDSY","kinase_name":"","source":"psite;hprd","string_score":627},{"sub_ensp":"ENSP00000354558","sub_name":"MTOR","sub_position":2446,"sub_region":"RSRTRTDSYSA","kinase_name":"AKT1;RPS6KB1","source":"psite;pelm;hprd","string_score":627},{"sub_ensp":"ENSP00000354558","sub_name":"MTOR","sub_position":2448,"sub_region":"RTRTDSYSAGQ","kinase_name":"AKT1;RPS6KB1","source":"psite;pelm;hprd","string_score":627},{"sub_ensp":"ENSP00000354558","sub_name":"MTOR","sub_position":2481,"sub_region":"PESIHSFIGDG","kinase_name":"MTOR","source":"psite;pelm;hprd","string_score":627},{"sub_ensp":"ENSP00000354916","sub_name":"CDC14A","sub_position":444,"sub_region":"QGSAVTLKTSK","kinase_name":"","source":"psite","string_score":443},{"sub_ensp":"ENSP00000357206","sub_name":"NES","sub_position":1175,"sub_region":"EGREESEAEAP","kinase_name":"","source":"psite","string_score":565},{"sub_ensp":"ENSP00000357206","sub_name":"NES","sub_position":1286,"sub_region":"ESREESEEDEL","kinase_name":"","source":"psite;hprd","string_score":565},{"sub_ensp":"ENSP00000357206","sub_name":"NES","sub_position":1445,"sub_region":"GSSVGSLQALS","kinase_name":"","source":"psite;hprd","string_score":565},{"sub_ensp":"ENSP00000357206","sub_name":"NES","sub_position":1492,"sub_region":"TESQDSAEPSG","kinase_name":"","source":"psite","string_score":565},{"sub_ensp":"ENSP00000357206","sub_name":"NES","sub_position":346,"sub_region":"GRRLGSLLPVL","kinase_name":"","source":"psite;hprd","string_score":565},{"sub_ensp":"ENSP00000357206","sub_name":"NES","sub_position":355,"sub_region":"VLSPTSLPSPL","kinase_name":"","source":"psite;hprd","string_score":565},{"sub_ensp":"ENSP00000357206","sub_name":"NES","sub_position":384,"sub_region":"QARTPTLASTP","kinase_name":"","source":"psite;pelm;hprd","string_score":565},{"sub_ensp":"ENSP00000357206","sub_name":"NES","sub_position":491,"sub_region":"GSRVFSICRGE","kinase_name":"","source":"psite","string_score":565},{"sub_ensp":"ENSP00000357206","sub_name":"NES","sub_position":746,"sub_region":"HKSLRSLEEQD","kinase_name":"","source":"psite;pelm;hprd","string_score":565},{"sub_ensp":"ENSP00000357206","sub_name":"NES","sub_position":768,"sub_region":"QQRRRSLGEQD","kinase_name":"","source":"psite;pelm;hprd","string_score":565},{"sub_ensp":"ENSP00000357206","sub_name":"NES","sub_position":823,"sub_region":"VKSLETEILES","kinase_name":"","source":"psite","string_score":565},{"sub_ensp":"ENSP00000357206","sub_name":"NES","sub_position":831,"sub_region":"LESLKSAGQEN","kinase_name":"","source":"psite","string_score":565},{"sub_ensp":"ENSP00000357206","sub_name":"NES","sub_position":845,"sub_region":"LKSPETQAPLW","kinase_name":"","source":"psite;pelm;hprd","string_score":565},{"sub_ensp":"ENSP00000357206","sub_name":"NES","sub_position":894,"sub_region":"QESLRSLGAWN","kinase_name":"","source":"psite","string_score":565},{"sub_ensp":"ENSP00000357206","sub_name":"NES","sub_position":934,"sub_region":"QESLRSLEEEG","kinase_name":"","source":"psite;hprd","string_score":565},{"sub_ensp":"ENSP00000362824","sub_name":"OGT","sub_position":20,"sub_region":"TKRMLSFQGLA","kinase_name":"CHEK1","source":"psite;pelm;hprd","string_score":910},{"sub_ensp":"ENSP00000362824","sub_name":"OGT","sub_position":454,"sub_region":"IASYRTALKLK","kinase_name":"","source":"psite","string_score":910},{"sub_ensp":"ENSP00000366997","sub_name":"DIS3","sub_position":599,"sub_region":"QLRIDSANMND","kinase_name":"","source":"psite","string_score":400},{"sub_ensp":"ENSP00000367301","sub_name":"NDP","sub_position":14,"sub_region":"SFSMLSLLVIM","kinase_name":"","source":"hprd","string_score":543},{"sub_ensp":"ENSP00000368174","sub_name":"MCM8","sub_position":630,"sub_region":"VARMNSQDSNT","kinase_name":"","source":"psite","string_score":517},{"sub_ensp":"ENSP00000368881","sub_name":"KIN","sub_position":247,"sub_region":"KESSQSSTQSK","kinase_name":"","source":"psite","string_score":423},{"sub_ensp":"ENSP00000368881","sub_name":"KIN","sub_position":248,"sub_region":"ESSQSSTQSKE","kinase_name":"","source":"psite","string_score":423},{"sub_ensp":"ENSP00000369600","sub_name":"FRY","sub_position":1983,"sub_region":"HQRSFSVPKKF","kinase_name":"","source":"psite","string_score":443},{"sub_ensp":"ENSP00000386161","sub_name":"WWOX","sub_position":12,"sub_region":"AGLDDTDSEDE","kinase_name":"","source":"psite","string_score":429},{"sub_ensp":"ENSP00000388340","sub_name":"CLINT1","sub_position":166,"sub_region":"GVSSDSVGGFR","kinase_name":"","source":"psite","string_score":430},{"sub_ensp":"ENSP00000388340","sub_name":"CLINT1","sub_position":234,"sub_region":"ERCSDSDEEKK","kinase_name":"","source":"psite;pelm;hprd","string_score":430},{"sub_ensp":"ENSP00000394624","sub_name":"OPRM1","sub_position":356,"sub_region":"ILRLKSVRMLS","kinase_name":"","source":"psite","string_score":508},{"sub_ensp":"ENSP00000394624","sub_name":"OPRM1","sub_position":361,"sub_region":"SVRMLSGSKEK","kinase_name":"CAMK2A","source":"psite","string_score":508},{"sub_ensp":"ENSP00000394624","sub_name":"OPRM1","sub_position":465,"sub_region":"RIRQNTRDHPS","kinase_name":"","source":"psite;hprd","string_score":508},{"sub_ensp":"ENSP00000418734","sub_name":"MYSM1","sub_position":218,"sub_region":"KIEKLSDDEEV","kinase_name":"","source":"psite;pelm;hprd","string_score":619}]
