[{"sub_ensp":"ENSP00000228682","sub_name":"GLI1","sub_position":544,"sub_region":"LERRSSSSSSI","kinase_name":"PRKACA","source":"psite","string_score":800},{"sub_ensp":"ENSP00000228682","sub_name":"GLI1","sub_position":560,"sub_region":"VSRRSSLASPF","kinase_name":"PRKACA","source":"psite","string_score":800},{"sub_ensp":"ENSP00000228682","sub_name":"GLI1","sub_position":640,"sub_region":"VTRRASDPAQA","kinase_name":"PRKACA","source":"psite","string_score":800},{"sub_ensp":"ENSP00000248975","sub_name":"YWHAH","sub_position":59,"sub_region":"GARRSSWRVIS","kinase_name":"","source":"psite;pelm","string_score":899},{"sub_ensp":"ENSP00000300161","sub_name":"YWHAB","sub_position":60,"sub_region":"GARRSSWRVIS","kinase_name":"PRKCD","source":"psite;pelm;hprd","string_score":900},{"sub_ensp":"ENSP00000306330","sub_name":"YWHAG","sub_position":59,"sub_region":"GARRSSWRVIS","kinase_name":"LATS2","source":"psite","string_score":899},{"sub_ensp":"ENSP00000309503","sub_name":"YWHAZ","sub_position":58,"sub_region":"GARRSSWRVVS","kinase_name":"AKT1;MAPKAPK2;PRKACA","source":"psite;pelm;hprd","string_score":900},{"sub_ensp":"ENSP00000332973","sub_name":"SMAD3","sub_position":388,"sub_region":"EYRRQTVTSTP","kinase_name":"","source":"psite","string_score":621},{"sub_ensp":"ENSP00000354586","sub_name":"GLI2","sub_position":808,"sub_region":"QERRDSSTSTV","kinase_name":"","source":"psite","string_score":899},{"sub_ensp":"ENSP00000354586","sub_name":"GLI2","sub_position":824,"sub_region":"VSRRSSGISPY","kinase_name":"","source":"psite","string_score":899},{"sub_ensp":"ENSP00000354586","sub_name":"GLI2","sub_position":941,"sub_region":"GPRRGSDGPTY","kinase_name":"","source":"psite","string_score":899},{"sub_ensp":"ENSP00000354586","sub_name":"GLI2","sub_position":970,"sub_region":"GARRASDPVRR","kinase_name":"","source":"psite","string_score":899}]
